EasyAsCache/__init__.py
EasyAsCache/aes.py
EasyAsCache/cache.py
EasyAsCache-0.0.3.dist-info/LICENSE
EasyAsCache-0.0.3.dist-info/METADATA
EasyAsCache-0.0.3.dist-info/WHEEL
EasyAsCache-0.0.3.dist-info/top_level.txt
EasyAsCache-0.0.3.dist-info/RECORD
