Metadata-Version: 2.1
Name: EasyAsCache
Version: 0.0.3
Summary: UNKNOWN
Home-page: UNKNOWN
Author: VeteranCode
Author-email: jacob.h.barrow@gmail.com
License: MIT
Platform: UNKNOWN
Classifier: License :: OSI Approved :: MIT License
Classifier: Programming Language :: Python
Classifier: Programming Language :: Python :: 3
License-File: LICENSE
